chi/__init__.py
chi/app.py
chi/argscope.py
chi/experiment.py
chi/function.py
chi/logger.py
chi/main.py
chi/model.py
chi/ops.py
chi/process.py
chi/subgraph.py
chi/util.py
chi/board/__init__.py
chi/board/experiment.py
chi/board/main.py
chi/board/resource.py
chi/board/server.py
chi/board/util.py
chi/rl/__init__.py
chi/rl/bdpg.py
chi/rl/ddpg.py
chi/rl/dqn.py
chi/rl/memory.py
chi/rl/util.py
chi/rl/legacy/__init__.py
chi/rl/legacy/agent.py
chi/rl/legacy/core.py
chi/rl/legacy/dashboard.py
chi/rl/legacy/ddpg.py
chi/rl/legacy/ddpg_test.py
chi/rl/legacy/filter_env.py
chi/rl/legacy/run.py
chi/rl/legacy/tensorfun.py
chi/rl/legacy/util.py
chi/rl/legacy/visualization.py
chi-0.2.data/scripts/chiboard
chi-0.2.dist-info/DESCRIPTION.rst
chi-0.2.dist-info/METADATA
chi-0.2.dist-info/RECORD
chi-0.2.dist-info/WHEEL
chi-0.2.dist-info/metadata.json
chi-0.2.dist-info/top_level.txt
legacy/__init__.py
legacy/bla.py
legacy/ddpg.py
legacy/ddpg_continuous.py
legacy/ddpg_convolutional.py
legacy/ddpg_old.py
legacy/model_function_class_prototype.py
legacy/subgraph_old.py
legacy/univtest.py
legacy/wgan.py
legacy/wgan_big.py
