Metadata-Version: 2.0
Name: chi
Version: 0.2
Summary: UNKNOWN
Home-page: https://github.com/rmst/chi
Author: Simon Ramstedt
Author-email: simonramstedt@gmail.com
License: MIT
Platform: UNKNOWN
Requires-Dist: flask (>=0.12)
Requires-Dist: flask-socketio
Requires-Dist: matplotlib (>=2.0)
Requires-Dist: tensorflow (>=1.0.1)
Requires-Dist: watchdog
Provides-Extra: rl
Requires-Dist: gym; extra == 'rl'
